ssgetpy/__init__.py
ssgetpy/__main__.py
ssgetpy/bundle.py
ssgetpy/config.py
ssgetpy/csvindex.py
ssgetpy/db.py
ssgetpy/dbinstance.py
ssgetpy/matrix.py
ssgetpy/query.py
ssgetpy-1.0rc2.dist-info/METADATA
ssgetpy-1.0rc2.dist-info/WHEEL
ssgetpy-1.0rc2.dist-info/entry_points.txt
ssgetpy-1.0rc2.dist-info/top_level.txt
ssgetpy-1.0rc2.dist-info/RECORD
