Metadata-Version: 2.1
Name: ssgetpy
Version: 1.0rc2
Summary: A Python interface to the SuiteSparse Matrix Collection
Home-page: http://www.github.com/drdarshan/ssgetpy
Author: Sudarshan Raghunathan
Author-email: darshan@alum.mit.edu
License: UNKNOWN
Platform: UNKNOWN
Classifier: Programming Language :: Python :: 3
Classifier: License :: OSI Approved :: MIT License
Classifier: Operating System :: OS Independent
Classifier: Topic :: Scientific/Engineering :: Mathematics
Requires-Python: >3.5.2
Requires-Dist: requests (>=2.22)
Requires-Dist: tqdm (>=4.41)
